gym_pool/__init__.py
gym_pool/envs/__init__.py
gym_pool/envs/ball.py
gym_pool/envs/collisions.py
gym_pool/envs/config.py
gym_pool/envs/cue.py
gym_pool/envs/cue_visible.py
gym_pool/envs/event.py
gym_pool/envs/gamestate.py
gym_pool/envs/gamestate_angle.py
gym_pool/envs/gamestate_continuous.py
gym_pool/envs/graphics.py
gym_pool/envs/main.py
gym_pool/envs/physics.py
gym_pool/envs/pool_env.py
gym_pool/envs/pool_env_3.py
gym_pool/envs/pool_env_angle.py
gym_pool/envs/pool_env_continuous.py
gym_pool/envs/pool_env_new_statespace.py
gym_pool/envs/soccer_empty_goal.py
gym_pool/envs/table_sprites.py
gym_pool/envs/utils.py
gym_pool-0.1.32.dist-info/LICENSE
gym_pool-0.1.32.dist-info/METADATA
gym_pool-0.1.32.dist-info/WHEEL
gym_pool-0.1.32.dist-info/top_level.txt
gym_pool-0.1.32.dist-info/RECORD
